      {"ID": "INV", "name": "Inventar", "surename": ""}
      {"ID": "ATH", "name": "Andrea", "surename": "Tholen"}
      {"ID": "MAR", "name": "Monika", "surename": "Arici"}
      {"ID": "DUS", "name": "Paul", "surename": "Dusik"}
      {"ID": "AEI", "name": "Andrea", "surename": "Eickhoff"}
      {"ID": "AGL", "name": "Annika", "surename": "Glade"}
      {"ID": "GGO", "name": "Günter", "surename": "Gospodarczyk"}
      {"ID": "CGU", "name": "Claudia", "surename": "Gueth"}
      {"ID": "ÖGÜ", "name": "Özge", "surename": "Güner"}
      {"ID": "AHA", "name": "Angelika", "surename": "Haas"}
      {"ID": "JHE", "name": "Judith", "surename": "Heimer"}
      {"ID": "AHI", "name": "Angelika", "surename": "Hilbig"}
      {"ID": "BHU", "name": "Beate", "surename": "Huppertz"}
      {"ID": "RKO", "name": "Raina", "surename": "Kohlberger-Veltrup"}
      {"ID": "NKO", "name": "Natalia", "surename": "Kolesnik"}
      {"ID": "BLA", "name": "Birgit", "surename": "Lahaye-Reiß"}
      {"ID": "CLI", "name": "Christiana", "surename": "Linke"}
      {"ID": "JMA", "name": "Jamileh", "surename": "Mahmoudi-Otaghvari"}
      {"ID": "UOR", "name": "Ulrike", "surename": "Ortmann-Zambanini"}
      {"ID": "ERI", "name": "Elisa", "surename": "Rissmann"}
      {"ID": "ARE", "name": "Anne", "surename": "Reiß-Hannott"}
      {"ID": "TSC", "name": "Terry", "surename": "Schepanski"}
      {"ID": "PSC", "name": "Petra", "surename": "Schleusener"}
      {"ID": "VSC", "name": "Verena", "surename": "Schmidt-Suijk"}
      {"ID": "LSC", "name": "Linda", "surename": "Schmitz"}
      {"ID": "HSI", "name": "Hubertine", "surename": "Simonis"}
      {"ID": "ASO", "name": "Andrea", "surename": "Sohn"}
      {"ID": "HTU", "name": "Hüseyin", "surename": "Turunc"}
      {"ID": "SWE", "name": "Stefanie", "surename": "Dr. Weber"}
      {"ID": "BWI", "name": "Brigitte", "surename": "Wicking-Reese"}
